spaces/__init__.py
spaces/_vendor/__init__.py
spaces/_vendor/codefind/LICENSE
spaces/_vendor/codefind/__init__.py
spaces/_vendor/codefind/registry.py
spaces/_vendor/codefind/version.py
spaces/_vendor/jurigged/LICENSE
spaces/_vendor/jurigged/__init__.py
spaces/_vendor/jurigged/codetools.py
spaces/_vendor/jurigged/parse.py
spaces/_vendor/jurigged/register.py
spaces/_vendor/jurigged/utils.py
spaces/_vendor/jurigged/version.py
spaces/_vendor/ovld/LICENSE
spaces/_vendor/ovld/__init__.py
spaces/_vendor/ovld/abc.py
spaces/_vendor/ovld/codegen.py
spaces/_vendor/ovld/core.py
spaces/_vendor/ovld/dependent.py
spaces/_vendor/ovld/medley.py
spaces/_vendor/ovld/mro.py
spaces/_vendor/ovld/py.typed
spaces/_vendor/ovld/recode.py
spaces/_vendor/ovld/signatures.py
spaces/_vendor/ovld/typemap.py
spaces/_vendor/ovld/types.py
spaces/_vendor/ovld/utils.py
spaces/_vendor/ovld/version.py
spaces/_vendor/sse_starlette/LICENSE
spaces/_vendor/sse_starlette/__init__.py
spaces/_vendor/sse_starlette/event.py
spaces/_vendor/sse_starlette/py.typed
spaces/_vendor/sse_starlette/sse.py
spaces/_vendor/sseclient/LICENSE
spaces/_vendor/sseclient/__init__.py
spaces/config.py
spaces/gradio.py
spaces/reloading/__init__.py
spaces/reloading/client.py
spaces/reloading/server.py
spaces/reloading/types.py
spaces/reloading/types.ts
spaces/utils.py
spaces/zero/__init__.py
spaces/zero/api.py
spaces/zero/client.py
spaces/zero/decorator.py
spaces/zero/gradio.py
spaces/zero/torch/__init__.py
spaces/zero/torch/aoti.py
spaces/zero/torch/bitsandbytes.py
spaces/zero/torch/bitsandbytes_legacy.py
spaces/zero/torch/cudart.py
spaces/zero/torch/packing.py
spaces/zero/torch/patching.py
spaces/zero/torch/patching_legacy.py
spaces/zero/torch/static.py
spaces/zero/torch/types.py
spaces/zero/torch/utils.py
spaces/zero/tqdm.py
spaces/zero/types.py
spaces/zero/utils.py
spaces/zero/wrappers.py
spaces-0.47.0.dist-info/METADATA
spaces-0.47.0.dist-info/WHEEL
spaces-0.47.0.dist-info/RECORD
