Metadata-Version: 2.4
Name: spaces
Version: 0.47.0
Summary: Utilities for Hugging Face Spaces
License: Apache-2.0
Author: Charles Bensimon
Author-email: charles@huggingface.co
Requires-Python: >=3.10,<3.15
Classifier: License :: OSI Approved :: Apache Software License
Classifier: Programming Language :: Python :: 3
Classifier: Programming Language :: Python :: 3.10
Classifier: Programming Language :: Python :: 3.11
Classifier: Programming Language :: Python :: 3.12
Classifier: Programming Language :: Python :: 3.13
Classifier: Programming Language :: Python :: 3.14
Requires-Dist: gradio
Requires-Dist: httpx (>=0.20)
Requires-Dist: packaging
Requires-Dist: psutil (>=2,<6)
Requires-Dist: pydantic (>=1,<3)
Requires-Dist: requests (>=2.19,<3.0)
Requires-Dist: typing-extensions (>=4,<5)
Project-URL: Homepage, https://huggingface.co
Project-URL: Repository, https://github.com/huggingface/huggingface_hub
